cursor_agent/.cursorrules
cursor_agent/.env.example
cursor_agent/__init__.py
cursor_agent/main.py
cursor_agent/requirements.txt
cursor_agent/tools/__init__.py
cursor_agent/tools/generate_changelog.py
cursor_agent/tools/llm_api.py
cursor_agent/tools/search_engine.py
cursor_agent/tools/update_cursor_agent.py
cursor_agent/tools/verify_setup.py
cursor_agent/tools/web_scraper.py
cursor_agent-0.1.4.dist-info/LICENSE
cursor_agent-0.1.4.dist-info/METADATA
cursor_agent-0.1.4.dist-info/WHEEL
cursor_agent-0.1.4.dist-info/entry_points.txt
cursor_agent-0.1.4.dist-info/top_level.txt
cursor_agent-0.1.4.dist-info/RECORD
