Metadata-Version: 2.2
Name: cursor-agent
Version: 0.1.4
Summary: A tool for initializing projects with Cursor agent capabilities
Home-page: https://github.com/grapeot/devin.cursorrules
Author: grapeot
Author-email: 
Project-URL: Bug Tracker, https://github.com/grapeot/devin.cursorrules/issues
Project-URL: Documentation, https://github.com/grapeot/devin.cursorrules#readme
Project-URL: Source Code, https://github.com/grapeot/devin.cursorrules
Keywords: cursor,agent,llm,ai,automation,development
Classifier: Development Status :: 4 - Beta
Classifier: Intended Audience :: Developers
Classifier: Topic :: Software Development :: Libraries :: Python Modules
Classifier: Topic :: Software Development :: Build Tools
Classifier: Topic :: Software Development :: Testing
Classifier: Programming Language :: Python :: 3
Classifier: Programming Language :: Python :: 3.8
Classifier: Programming Language :: Python :: 3.9
Classifier: Programming Language :: Python :: 3.10
Classifier: Programming Language :: Python :: 3.11
Classifier: License :: OSI Approved :: MIT License
Classifier: Operating System :: OS Independent
Classifier: Natural Language :: English
Classifier: Environment :: Console
Requires-Python: >=3.8
License-File: LICENSE
Requires-Dist: requests>=2.31.0
Requires-Dist: playwright>=1.40.0
Requires-Dist: anthropic>=0.7.0
Requires-Dist: openai>=1.3.0
Requires-Dist: google-generativeai>=0.3.0
Requires-Dist: python-dotenv>=1.0.0
Requires-Dist: duckduckgo-search>=4.1.1
Requires-Dist: html5lib>=1.1
Requires-Dist: packaging>=23.2
Dynamic: author
Dynamic: classifier
Dynamic: description
Dynamic: description-content-type
Dynamic: home-page
Dynamic: keywords
Dynamic: project-url
Dynamic: requires-dist
Dynamic: requires-python
Dynamic: summary
